roon/__init__.py
roon/__main__.py
roon/allpy2json.py
roon/builtin2json.py
roon/builtin_basic.py
roon/builtin_uproot.py
roon/engine.py
roon/global_store.py
roon/source2json.py
roon/static/nodes/__init__.py
roon/static/nodes/basic.py
roon/static/nodes/example_functions.py
roon/static/nodes/matplotlib_nodes.py
roon/static/nodes/uproot_nodes.py
roon/static/svelte/example_plot.svg
roon/static/svelte/favicon.png
roon/static/svelte/global.css
roon/static/svelte/index.html
roon/static/svelte/__pycache__/matplotlib_nodes.cpython-39.pyc
roon/static/svelte/__pycache__/uproot_nodes.cpython-39.pyc
roon/static/svelte/build/bundle.css
roon/static/svelte/build/bundle.js
roon/static/svelte/build/bundle.js.map
roon-0.5.1.dist-info/licenses/LICENSE
roon-0.5.1.dist-info/METADATA
roon-0.5.1.dist-info/WHEEL
roon-0.5.1.dist-info/entry_points.txt
roon-0.5.1.dist-info/top_level.txt
roon-0.5.1.dist-info/RECORD
