Metadata-Version: 2.4
Name: roon
Version: 0.5.1
Summary: A modern node based python editor and REPL for physics, education, and data analysis
Author: James Daniel Brandenburg
License: MIT
Requires-Python: >=3.8
License-File: LICENSE
Requires-Dist: pywebview
Dynamic: license-file
